wattpad/__init__.py
wattpad/errors.py
wattpad/backend/__init__.py
wattpad/backend/core.py
wattpad/backend/query_builder.py
wattpad/modals/__init__.py
wattpad/modals/part.py
wattpad/modals/published_part.py
wattpad/modals/rendered_part_skeleton.py
wattpad/modals/story.py
wattpad/modals/tags.py
wattpad/modals/user.py
wattpad_api-1.0.1.dist-info/LICENSE.txt
wattpad_api-1.0.1.dist-info/METADATA
wattpad_api-1.0.1.dist-info/WHEEL
wattpad_api-1.0.1.dist-info/top_level.txt
wattpad_api-1.0.1.dist-info/RECORD
