Metadata-Version: 2.1
Name: wattpad-api
Version: 1.0.1
Summary: A no-compromises wrapper for the Wattpad API
Home-page: https://github.com/Advik-B/wattpad-api
Author: Advik
Author-email: <advik.b@gmail.com>
Keywords: Wattpad,Wattpad Wrapper,Watppad API,API,Wrapper
Classifier: Intended Audience :: Developers
Classifier: Programming Language :: Python :: 3
Classifier: License :: OSI Approved :: MIT License
Classifier: Operating System :: OS Independent
License-File: LICENSE.txt
Requires-Dist: requests
Requires-Dist: diskcache
Requires-Dist: path
Requires-Dist: certifi
Requires-Dist: beautifulsoup4
